{
  "Adialer.C":      { "category": "Trojan",        "severity": "Low"    },
  "Agent.FYI":      { "category": "Trojan",        "severity": "High"   },
  "Allaple.A":      { "category": "Other Malware", "severity": "High"   },
  "Allaple.L":      { "category": "Other Malware", "severity": "High"   },
  "Alueron.gen!J":  { "category": "Trojan",        "severity": "High"   },
  "Autorun.K":      { "category": "Trojan",        "severity": "High"   },
  "C2LOP.P":        { "category": "Trojan",        "severity": "Medium" },
  "C2LOP.gen!g":    { "category": "Trojan",        "severity": "Medium" },
  "Dialplatform.B": { "category": "Trojan",        "severity": "Medium" },
  "Dontovo.A":      { "category": "Trojan",        "severity": "High"   },
  "Fakerean":       { "category": "Other Malware", "severity": "High"   },
  "Instantaccess":  { "category": "Other Malware", "severity": "Low"    },
  "Lolyda.AA1":     { "category": "Trojan",        "severity": "High"   },
  "Lolyda.AA2":     { "category": "Trojan",        "severity": "High"   },
  "Lolyda.AA3":     { "category": "Trojan",        "severity": "High"   },
  "Lolyda.AT":      { "category": "Trojan",        "severity": "High"   },
  "Malex.gen!J":    { "category": "Trojan",        "severity": "High"   },
  "Obfuscator.AD":  { "category": "Trojan",        "severity": "Medium" },
  "Rbot!gen":       { "category": "Trojan",        "severity": "High"   },
  "Skintrim.N":     { "category": "Trojan",        "severity": "Medium" },
  "Swizzor.gen!E":  { "category": "Other Malware", "severity": "High"   },
  "Swizzor.gen!I":  { "category": "Other Malware", "severity": "High"   },
  "VB.AT":          { "category": "Trojan",        "severity": "Low"    },
  "Wintrim.BX":     { "category": "Trojan",        "severity": "Medium" },
  "Yuner.A":        { "category": "Trojan",        "severity": "High"   }
}
